command.py
create_files.py
setup.py
celestis.egg-info/PKG-INFO
celestis.egg-info/SOURCES.txt
celestis.egg-info/dependency_links.txt
celestis.egg-info/entry_points.txt
celestis.egg-info/requires.txt
celestis.egg-info/top_level.txt
controller/request.py
model/auth.py
model/crud.py
model/database.py
model/exceptions.py
view/templates.py