Metadata-Version: 2.1
Name: celestis
Version: 2.7
Summary: A simple backend framework built using python
Author: Aryaan Hegde
Author-email: aryhegde@gmail.com
